fill_in_blanks_component/__init__.py
fill_in_blanks_component/frontend/dist/index.html
fill_in_blanks_component/frontend/dist/assets/index.css
fill_in_blanks_component/frontend/dist/assets/index.js
streamlit_fill_in_blanks-0.1.3.dist-info/licenses/LICENSE
streamlit_fill_in_blanks-0.1.3.dist-info/METADATA
streamlit_fill_in_blanks-0.1.3.dist-info/WHEEL
streamlit_fill_in_blanks-0.1.3.dist-info/top_level.txt
streamlit_fill_in_blanks-0.1.3.dist-info/RECORD
